plurk_dice/__init__.py
plurk_dice/dice.py
plurk_dice/download.py
plurk_dice-0.0.3.dist-info/METADATA
plurk_dice-0.0.3.dist-info/WHEEL
plurk_dice-0.0.3.dist-info/top_level.txt
plurk_dice-0.0.3.dist-info/RECORD
