Metadata-Version: 2.1
Name: plurk-dice
Version: 0.0.3
Summary: A third-party Python API of Plurk Dice Emojis
Home-page: https://github.com/Plurk-Project/plurk-dice
Author: SheiUn
Author-email: develop@sheiun.me
License: UNKNOWN
Platform: UNKNOWN
Classifier: Programming Language :: Python :: 3
Classifier: License :: OSI Approved :: MIT License
Classifier: Operating System :: OS Independent
Requires-Python: >=3.7
Requires-Dist: requests
